{

    "scene-manager": {
        "settings": {
            "parse_mode": "Markdown",
            "delete_after_send": true
        },
        "pages": {
            "start": {
                "title": "",
                "content": "Добро пожаловать в игру SEG!\nSEG (Simple Economic Game) — это многопользовательская экономическая игра в реальном времени, представляющая собой симулятор управления компанией в конкурентной среде.\n\n Концепция игры:\nИгра представляет собой пошаговую экономическую стратегию, где игроки управляют компаниями, добывают ресурсы, производят товары, торгуют и конкурируют между собой на общем игровом поле.\n\nВведиие код для подключения к игровой сессии: ",
                "to_pages": {}
            },
            "name-enter": { // +
                "title": "",
                "content": "Подключение успешно\nВведите ваше имя для продолжения: ",
                "to_pages": {
                    "start": "Указать другой код"
                }
            },
            "company-option": { 
                "title": "",
                "content": "Выберите - создать или присоединиться",
                "to_pages": {
                    "company-create": "Создать",
                    "company-join": "Присоединится"
                }
            },
            "company-create": {   // +
                "title": "",
                "content": "Введите название компании: ",
                "to_pages": {
                    "company-option": "Вернуться к выбору"
                }
            },
            "company-join": {   // +
                "title": "",
                "content": "Введите секретный код: ",
                "to_pages": {
                    "company-option": "Вернуться к выбору"
                }
            },
            "wait-start-page": {   // +
                "title": "",
                "content": "**Ожидание начала игры...**\n\n",
                "to_pages": {
                    "company-option": "Вернуться к выбору"
                }
            },
            "select-cell-page": {   // +
                "title": "",
                "content": "Выберите клетку, на которой будет ваша располагаться ваша компания: ",
                "to_pages": {}
            },
            "wait-select-cell-page": {
                "title": "",
                "content": "Ожидание выбора клетки владельцем...",
                "to_pages": {}
            },
            "wait-game-stage-page": {   // +
                "title": "",
                "content": "Вы выбрали клетку. Ожидание начала игрового этапа...",
                "to_pages": {}
            },
            "main-page":{ 
                "title": "",
                "content": "Меню управления компанией",
                "to_pages": {
                    "bank-menu": "🏦 Банк",
                    "exchange-menu": "📈 Биржа",
                    "contract-menu": "📋 Контракты",
                    "factory-menu": "🏭 Управление заводами",
                    "upgrade-cell-menu": "🔧 Улучшение ячейки",
                    "about-info-menu": "👥 Общая информация",
                    "logistics-menu": "🚚 Логистика",
                    "cities-menu": "🏙️ Города"
                }
            },
            "about-info-menu": {
                "title": "",
                "content": "jh",
                "to_pages": {
                    "stage-info-page": "↪️ Назад",
                    "cells-info-page": "↪️ Назад",
                    "inventory-page": "↪️ Назад",
                    "main-page": "↪️ Назад"
                    
                }
            }
        }
    }

}